{
  "nodes": {
    "SitePage /dev-404-page/": {
      "path": "/dev-404-page/",
      "id": "SitePage /dev-404-page/",
      "parent": null,
      "children": [],
      "internal": {
        "type": "SitePage",
        "contentDigest": "f91d29e10ba680b413138cf9ed86e655",
        "owner": "internal-data-bridge"
      }
    },
    "d48d1c52-fe48-53cb-8f08-aa4b47dde5a5": {
      "resolve": "/Users/randyphallla/Documents/GitHub/randyphalla.github.io/node_modules/gatsby/dist/internal-plugins/dev-404-page",
      "id": "d48d1c52-fe48-53cb-8f08-aa4b47dde5a5",
      "name": "dev-404-page",
      "version": "1.0.0",
      "pluginOptions": {
        "plugins": []
      },
      "nodeAPIs": [
        "createPagesStatefully"
      ],
      "browserAPIs": [],
      "ssrAPIs": [],
      "pluginFilepath": "/Users/randyphallla/Documents/GitHub/randyphalla.github.io/node_modules/gatsby/dist/internal-plugins/dev-404-page",
      "packageJson": {
        "name": "dev-404-page",
        "description": "Internal plugin to add a 404 page in development with helpful information",
        "version": "1.0.0",
        "main": "index.js",
        "author": "Kyle Mathews <mathews.kyle@gmail.com>",
        "license": "MIT",
        "dependencies": [],
        "devDependencies": [],
        "peerDependencies": [],
        "optionalDependecies": [],
        "bundledDependecies": []
      },
      "parent": null,
      "children": [],
      "internal": {
        "contentDigest": "3248ac5db3649efb2c3d3c6db441451a",
        "type": "SitePlugin",
        "owner": "internal-data-bridge"
      }
    },
    "1fc32581-893a-55e8-8927-bcd667e2b700": {
      "resolve": "/Users/randyphallla/Documents/GitHub/randyphalla.github.io/node_modules/gatsby/dist/internal-plugins/load-babel-config",
      "id": "1fc32581-893a-55e8-8927-bcd667e2b700",
      "name": "load-babel-config",
      "version": "1.0.0",
      "pluginOptions": {
        "plugins": []
      },
      "nodeAPIs": [
        "onPreBootstrap"
      ],
      "browserAPIs": [],
      "ssrAPIs": [],
      "pluginFilepath": "/Users/randyphallla/Documents/GitHub/randyphalla.github.io/node_modules/gatsby/dist/internal-plugins/load-babel-config",
      "packageJson": {
        "name": "load-babel-config",
        "description": "Internal plugin that handles loading Babel configs",
        "version": "1.0.0",
        "main": "index.js",
        "author": "Kyle Mathews <mathews.kyle@gmail.com>",
        "license": "MIT",
        "dependencies": [],
        "devDependencies": [],
        "peerDependencies": [],
        "optionalDependecies": [],
        "bundledDependecies": []
      },
      "parent": null,
      "children": [],
      "internal": {
        "contentDigest": "38b84438586168b8aaf63f4b2201a07f",
        "type": "SitePlugin",
        "owner": "internal-data-bridge"
      }
    },
    "a5079d69-ba80-53dc-82f9-0f440bd5448c": {
      "resolve": "/Users/randyphallla/Documents/GitHub/randyphalla.github.io/node_modules/gatsby/dist/internal-plugins/internal-data-bridge",
      "id": "a5079d69-ba80-53dc-82f9-0f440bd5448c",
      "name": "internal-data-bridge",
      "version": "1.0.0",
      "pluginOptions": {
        "plugins": []
      },
      "nodeAPIs": [
        "sourceNodes",
        "onCreatePage"
      ],
      "browserAPIs": [],
      "ssrAPIs": [],
      "pluginFilepath": "/Users/randyphallla/Documents/GitHub/randyphalla.github.io/node_modules/gatsby/dist/internal-plugins/internal-data-bridge",
      "packageJson": {
        "name": "internal-data-bridge",
        "description": "An internal Gatsby plugin which creates data nodes from internal data",
        "version": "1.0.0",
        "main": "index.js",
        "author": "Kyle Mathews <mathews.kyle@gmail.com>",
        "license": "MIT",
        "dependencies": [],
        "devDependencies": [],
        "peerDependencies": [],
        "optionalDependecies": [],
        "bundledDependecies": []
      },
      "parent": null,
      "children": [],
      "internal": {
        "contentDigest": "46c0b1195a12c6708f9d01e9fed98363",
        "type": "SitePlugin",
        "owner": "internal-data-bridge"
      }
    },
    "f795702c-a3b8-5a88-88ee-5d06019d44fa": {
      "resolve": "/Users/randyphallla/Documents/GitHub/randyphalla.github.io/node_modules/gatsby/dist/internal-plugins/prod-404",
      "id": "f795702c-a3b8-5a88-88ee-5d06019d44fa",
      "name": "prod-404",
      "version": "1.0.0",
      "pluginOptions": {
        "plugins": []
      },
      "nodeAPIs": [
        "onCreatePage"
      ],
      "browserAPIs": [],
      "ssrAPIs": [],
      "pluginFilepath": "/Users/randyphallla/Documents/GitHub/randyphalla.github.io/node_modules/gatsby/dist/internal-plugins/prod-404",
      "packageJson": {
        "name": "prod-404",
        "description": "Internal plugin to detect various flavors of 404 pages and ensure there's a 404.html path created as well to ensure compatability with static hosts",
        "version": "1.0.0",
        "main": "index.js",
        "author": "Kyle Mathews <mathews.kyle@gmail.com>",
        "license": "MIT",
        "dependencies": [],
        "devDependencies": [],
        "peerDependencies": [],
        "optionalDependecies": [],
        "bundledDependecies": []
      },
      "parent": null,
      "children": [],
      "internal": {
        "contentDigest": "b65d71cebdac5ce5a5a7307969b2def2",
        "type": "SitePlugin",
        "owner": "internal-data-bridge"
      }
    },
    "84dad27f-1d44-51fc-ac56-4db2e5222995": {
      "resolve": "/Users/randyphallla/Documents/GitHub/randyphalla.github.io/node_modules/gatsby/dist/internal-plugins/query-runner",
      "id": "84dad27f-1d44-51fc-ac56-4db2e5222995",
      "name": "query-runner",
      "version": "1.0.0",
      "pluginOptions": {
        "plugins": []
      },
      "nodeAPIs": [
        "onCreatePage"
      ],
      "browserAPIs": [],
      "ssrAPIs": [],
      "pluginFilepath": "/Users/randyphallla/Documents/GitHub/randyphalla.github.io/node_modules/gatsby/dist/internal-plugins/query-runner",
      "packageJson": {
        "name": "query-runner",
        "description": "Internal plugin for running queries",
        "version": "1.0.0",
        "main": "index.js",
        "author": "",
        "license": "MIT",
        "dependencies": [],
        "devDependencies": [],
        "peerDependencies": [],
        "optionalDependecies": [],
        "bundledDependecies": []
      },
      "parent": null,
      "children": [],
      "internal": {
        "contentDigest": "1d0b16c7a4eb83b15a7144791f3130a5",
        "type": "SitePlugin",
        "owner": "internal-data-bridge"
      }
    },
    "6f4b2fa9-66b5-5205-a03f-140005a2cfe5": {
      "resolve": "/Users/randyphallla/Documents/GitHub/randyphalla.github.io/node_modules/gatsby/dist/internal-plugins/webpack-theme-component-shadowing",
      "id": "6f4b2fa9-66b5-5205-a03f-140005a2cfe5",
      "name": "webpack-theme-component-shadowing",
      "version": "1.0.0",
      "pluginOptions": {
        "plugins": []
      },
      "nodeAPIs": [
        "onCreateWebpackConfig"
      ],
      "browserAPIs": [],
      "ssrAPIs": [],
      "pluginFilepath": "/Users/randyphallla/Documents/GitHub/randyphalla.github.io/node_modules/gatsby/dist/internal-plugins/webpack-theme-component-shadowing",
      "packageJson": {
        "name": "webpack-theme-component-shadowing",
        "description": "An internal Gatsby plugin which handles configuring webpack to ensure theme components fall back from the user's site to theme modules.",
        "version": "1.0.0",
        "main": "index.js",
        "author": "Chris Biscardi <chris@christopherbiscardi.com>",
        "license": "MIT",
        "dependencies": [],
        "devDependencies": [],
        "peerDependencies": [],
        "optionalDependecies": [],
        "bundledDependecies": []
      },
      "parent": null,
      "children": [],
      "internal": {
        "contentDigest": "413103df7a7c67366bfa95084a56cd5f",
        "type": "SitePlugin",
        "owner": "internal-data-bridge"
      }
    },
    "1943ff2f-9c0c-558d-8d0c-006603e8106a": {
      "resolve": "/Users/randyphallla/Documents/GitHub/randyphalla.github.io/node_modules/gatsby-plugin-react-helmet",
      "id": "1943ff2f-9c0c-558d-8d0c-006603e8106a",
      "name": "gatsby-plugin-react-helmet",
      "version": "3.0.8",
      "pluginOptions": {
        "plugins": []
      },
      "nodeAPIs": [],
      "browserAPIs": [],
      "ssrAPIs": [
        "onRenderBody"
      ],
      "pluginFilepath": "/Users/randyphallla/Documents/GitHub/randyphalla.github.io/node_modules/gatsby-plugin-react-helmet",
      "packageJson": {
        "name": "gatsby-plugin-react-helmet",
        "description": "Manage document head data with react-helmet. Provides drop-in server rendering support for Gatsby.",
        "version": "3.0.8",
        "main": "index.js",
        "keywords": [
          "gatsby",
          "gatsby-plugin",
          "favicon",
          "react-helmet",
          "seo",
          "document",
          "head",
          "title",
          "meta",
          "link",
          "script",
          "base",
          "noscript",
          "style"
        ],
        "author": {
          "name": "Kyle Mathews",
          "email": "matthews.kyle@gmail.com"
        },
        "license": "MIT",
        "dependencies": [
          {
            "name": "@babel/runtime",
            "version": "^7.0.0"
          }
        ],
        "devDependencies": [
          {
            "name": "@babel/cli",
            "version": "^7.0.0"
          },
          {
            "name": "@babel/core",
            "version": "^7.0.0"
          },
          {
            "name": "babel-preset-gatsby-package",
            "version": "^0.1.3"
          },
          {
            "name": "cross-env",
            "version": "^5.1.4"
          }
        ],
        "peerDependencies": [
          {
            "name": "gatsby",
            "version": "^2.0.0"
          },
          {
            "name": "react-helmet",
            "version": "^5.1.3"
          }
        ],
        "optionalDependecies": [],
        "bundledDependecies": []
      },
      "parent": null,
      "children": [],
      "internal": {
        "contentDigest": "88f326845116894432a94e28dee910fe",
        "type": "SitePlugin",
        "owner": "internal-data-bridge"
      }
    },
    "3d2081ad-728e-5303-8d30-d0c8fab8d07a": {
      "resolve": "/Users/randyphallla/Documents/GitHub/randyphalla.github.io/node_modules/gatsby-source-filesystem",
      "id": "3d2081ad-728e-5303-8d30-d0c8fab8d07a",
      "name": "gatsby-source-filesystem",
      "version": "2.0.23",
      "pluginOptions": {
        "plugins": [],
        "name": "images",
        "path": "/Users/randyphallla/Documents/GitHub/randyphalla.github.io/src/images"
      },
      "nodeAPIs": [
        "sourceNodes",
        "setFieldsOnGraphQLNodeType"
      ],
      "browserAPIs": [],
      "ssrAPIs": [],
      "pluginFilepath": "/Users/randyphallla/Documents/GitHub/randyphalla.github.io/node_modules/gatsby-source-filesystem",
      "packageJson": {
        "name": "gatsby-source-filesystem",
        "description": "Gatsby plugin which parses files within a directory for further parsing by other plugins",
        "version": "2.0.23",
        "keywords": [
          "gatsby",
          "gatsby-plugin"
        ],
        "author": {
          "name": "Kyle Mathews",
          "email": "mathews.kyle@gmail.com"
        },
        "license": "MIT",
        "dependencies": [
          {
            "name": "@babel/runtime",
            "version": "^7.0.0"
          },
          {
            "name": "better-queue",
            "version": "^3.8.7"
          },
          {
            "name": "bluebird",
            "version": "^3.5.0"
          },
          {
            "name": "chokidar",
            "version": "^2.1.2"
          },
          {
            "name": "file-type",
            "version": "^10.2.0"
          },
          {
            "name": "fs-extra",
            "version": "^5.0.0"
          },
          {
            "name": "got",
            "version": "^7.1.0"
          },
          {
            "name": "md5-file",
            "version": "^3.1.1"
          },
          {
            "name": "mime",
            "version": "^2.2.0"
          },
          {
            "name": "pretty-bytes",
            "version": "^4.0.2"
          },
          {
            "name": "progress",
            "version": "^1.1.8"
          },
          {
            "name": "read-chunk",
            "version": "^3.0.0"
          },
          {
            "name": "slash",
            "version": "^1.0.0"
          },
          {
            "name": "valid-url",
            "version": "^1.0.9"
          },
          {
            "name": "xstate",
            "version": "^3.1.0"
          }
        ],
        "devDependencies": [
          {
            "name": "@babel/cli",
            "version": "^7.0.0"
          },
          {
            "name": "@babel/core",
            "version": "^7.0.0"
          },
          {
            "name": "babel-preset-gatsby-package",
            "version": "^0.1.3"
          },
          {
            "name": "cross-env",
            "version": "^5.1.4"
          }
        ],
        "peerDependencies": [
          {
            "name": "gatsby",
            "version": "^2.0.0"
          }
        ],
        "optionalDependecies": [],
        "bundledDependecies": []
      },
      "parent": null,
      "children": [],
      "internal": {
        "contentDigest": "4c985135823fc11e1b9ee136c4f95446",
        "type": "SitePlugin",
        "owner": "internal-data-bridge"
      }
    },
    "da3d06eb-685e-5c77-ae1d-750eb6a2e4a9": {
      "resolve": "/Users/randyphallla/Documents/GitHub/randyphalla.github.io/node_modules/gatsby-transformer-sharp",
      "id": "da3d06eb-685e-5c77-ae1d-750eb6a2e4a9",
      "name": "gatsby-transformer-sharp",
      "version": "2.1.15",
      "pluginOptions": {
        "plugins": []
      },
      "nodeAPIs": [
        "onCreateNode",
        "setFieldsOnGraphQLNodeType",
        "onPreExtractQueries"
      ],
      "browserAPIs": [],
      "ssrAPIs": [],
      "pluginFilepath": "/Users/randyphallla/Documents/GitHub/randyphalla.github.io/node_modules/gatsby-transformer-sharp",
      "packageJson": {
        "name": "gatsby-transformer-sharp",
        "description": "Gatsby transformer plugin for images using Sharp",
        "version": "2.1.15",
        "keywords": [
          "gatsby",
          "gatsby-plugin",
          "image",
          "sharp"
        ],
        "author": {
          "name": "Kyle Mathews",
          "email": "mathews.kyle@gmail.com"
        },
        "license": "MIT",
        "dependencies": [
          {
            "name": "@babel/runtime",
            "version": "^7.0.0"
          },
          {
            "name": "bluebird",
            "version": "^3.5.0"
          },
          {
            "name": "fs-extra",
            "version": "^7.0.0"
          },
          {
            "name": "potrace",
            "version": "^2.1.1"
          },
          {
            "name": "probe-image-size",
            "version": "^4.0.0"
          },
          {
            "name": "sharp",
            "version": "^0.21.3"
          }
        ],
        "devDependencies": [
          {
            "name": "@babel/cli",
            "version": "^7.0.0"
          },
          {
            "name": "@babel/core",
            "version": "^7.0.0"
          },
          {
            "name": "babel-preset-gatsby-package",
            "version": "^0.1.3"
          },
          {
            "name": "cross-env",
            "version": "^5.1.4"
          }
        ],
        "peerDependencies": [
          {
            "name": "gatsby",
            "version": "^2.0.33"
          },
          {
            "name": "gatsby-plugin-sharp",
            "version": "^2.0.0-beta.3"
          }
        ],
        "optionalDependecies": [],
        "bundledDependecies": []
      },
      "parent": null,
      "children": [],
      "internal": {
        "contentDigest": "7ad39469907323d4b19daf2878344a33",
        "type": "SitePlugin",
        "owner": "internal-data-bridge"
      }
    },
    "84d6154d-4241-556c-a679-cc8339cac100": {
      "resolve": "/Users/randyphallla/Documents/GitHub/randyphalla.github.io/node_modules/gatsby-plugin-sharp",
      "id": "84d6154d-4241-556c-a679-cc8339cac100",
      "name": "gatsby-plugin-sharp",
      "version": "2.0.25",
      "pluginOptions": {
        "plugins": []
      },
      "nodeAPIs": [
        "onPreInit"
      ],
      "browserAPIs": [],
      "ssrAPIs": [],
      "pluginFilepath": "/Users/randyphallla/Documents/GitHub/randyphalla.github.io/node_modules/gatsby-plugin-sharp",
      "packageJson": {
        "name": "gatsby-plugin-sharp",
        "description": "Wrapper of the Sharp image manipulation library for Gatsby plugins",
        "version": "2.0.25",
        "main": "index.js",
        "keywords": [
          "gatsby",
          "gatsby-plugin",
          "image",
          "sharp"
        ],
        "author": {
          "name": "Kyle Mathews",
          "email": "mathews.kyle@gmail.com"
        },
        "license": "MIT",
        "dependencies": [
          {
            "name": "@babel/runtime",
            "version": "^7.0.0"
          },
          {
            "name": "async",
            "version": "^2.1.2"
          },
          {
            "name": "bluebird",
            "version": "^3.5.0"
          },
          {
            "name": "fs-exists-cached",
            "version": "^1.0.0"
          },
          {
            "name": "fs-extra",
            "version": "^7.0.0"
          },
          {
            "name": "imagemin",
            "version": "^6.0.0"
          },
          {
            "name": "imagemin-mozjpeg",
            "version": "^8.0.0"
          },
          {
            "name": "imagemin-pngquant",
            "version": "^6.0.0"
          },
          {
            "name": "imagemin-webp",
            "version": "^5.0.0"
          },
          {
            "name": "lodash",
            "version": "^4.17.10"
          },
          {
            "name": "mini-svg-data-uri",
            "version": "^1.0.0"
          },
          {
            "name": "potrace",
            "version": "^2.1.1"
          },
          {
            "name": "probe-image-size",
            "version": "^4.0.0"
          },
          {
            "name": "progress",
            "version": "^1.1.8"
          },
          {
            "name": "sharp",
            "version": "^0.21.3"
          },
          {
            "name": "svgo",
            "version": "^0.7.2"
          }
        ],
        "devDependencies": [
          {
            "name": "@babel/cli",
            "version": "^7.0.0"
          },
          {
            "name": "@babel/core",
            "version": "^7.0.0"
          },
          {
            "name": "babel-preset-gatsby-package",
            "version": "^0.1.3"
          },
          {
            "name": "cross-env",
            "version": "^5.1.4"
          }
        ],
        "peerDependencies": [
          {
            "name": "gatsby",
            "version": "^2.0.0"
          }
        ],
        "optionalDependecies": [],
        "bundledDependecies": []
      },
      "parent": null,
      "children": [],
      "internal": {
        "contentDigest": "8d8f99d3aa8001029309589273ecee0e",
        "type": "SitePlugin",
        "owner": "internal-data-bridge"
      }
    },
    "2513aa23-4bad-5f44-b0fc-fc6e87a81f91": {
      "resolve": "/Users/randyphallla/Documents/GitHub/randyphalla.github.io/node_modules/gatsby-plugin-sass",
      "id": "2513aa23-4bad-5f44-b0fc-fc6e87a81f91",
      "name": "gatsby-plugin-sass",
      "version": "2.0.10",
      "pluginOptions": {
        "plugins": [],
        "implementation": {
          "info": "dart-sass\t1.17.2\t(Sass Compiler)\t[Dart]\ndart2js\t2.1.1\t(Dart Compiler)\t[Dart]",
          "types": {}
        }
      },
      "nodeAPIs": [
        "onCreateWebpackConfig"
      ],
      "browserAPIs": [],
      "ssrAPIs": [],
      "pluginFilepath": "/Users/randyphallla/Documents/GitHub/randyphalla.github.io/node_modules/gatsby-plugin-sass",
      "packageJson": {
        "name": "gatsby-plugin-sass",
        "description": "Gatsby plugin to handle scss/sass files",
        "version": "2.0.10",
        "main": "index.js",
        "keywords": [
          "gatsby",
          "gatsby-plugin",
          "sass",
          "scss"
        ],
        "author": {
          "name": "Daniel Farrell",
          "email": "daniel@mobelux.com"
        },
        "license": "MIT",
        "dependencies": [
          {
            "name": "@babel/runtime",
            "version": "^7.0.0"
          },
          {
            "name": "sass-loader",
            "version": "^7.0.1"
          }
        ],
        "devDependencies": [
          {
            "name": "@babel/cli",
            "version": "^7.0.0"
          },
          {
            "name": "@babel/core",
            "version": "^7.0.0"
          },
          {
            "name": "babel-preset-gatsby-package",
            "version": "^0.1.3"
          },
          {
            "name": "cross-env",
            "version": "^5.1.4"
          }
        ],
        "peerDependencies": [
          {
            "name": "gatsby",
            "version": "^2.0.0"
          },
          {
            "name": "node-sass",
            "version": "^4.9.0"
          }
        ],
        "optionalDependecies": [],
        "bundledDependecies": []
      },
      "parent": null,
      "children": [],
      "internal": {
        "contentDigest": "7eaf3d402ee4eef7e7e67e88a40b40f5",
        "type": "SitePlugin",
        "owner": "internal-data-bridge"
      }
    },
    "112c12f8-b222-509b-abe0-dfe93a905df9": {
      "resolve": "/Users/randyphallla/Documents/GitHub/randyphalla.github.io/node_modules/gatsby-plugin-manifest",
      "id": "112c12f8-b222-509b-abe0-dfe93a905df9",
      "name": "gatsby-plugin-manifest",
      "version": "2.0.22",
      "pluginOptions": {
        "plugins": [],
        "name": "gatsby-starter-default",
        "short_name": "starter",
        "start_url": "/",
        "background_color": "#663399",
        "theme_color": "#663399",
        "display": "minimal-ui",
        "icon": "src/images/gatsby-icon.png"
      },
      "nodeAPIs": [
        "onPostBootstrap"
      ],
      "browserAPIs": [],
      "ssrAPIs": [
        "onRenderBody"
      ],
      "pluginFilepath": "/Users/randyphallla/Documents/GitHub/randyphalla.github.io/node_modules/gatsby-plugin-manifest",
      "packageJson": {
        "name": "gatsby-plugin-manifest",
        "description": "Gatsby plugin which adds a manifest.webmanifest to make sites progressive web apps",
        "version": "2.0.22",
        "main": "index.js",
        "keywords": [
          "gatsby",
          "gatsby-plugin",
          "favicon",
          "icons",
          "manifest.webmanifest",
          "progressive-web-app",
          "pwa"
        ],
        "author": {
          "name": "Kyle Mathews",
          "email": "mathews.kyle@gmail.com"
        },
        "license": "MIT",
        "dependencies": [
          {
            "name": "@babel/runtime",
            "version": "^7.0.0"
          },
          {
            "name": "bluebird",
            "version": "^3.5.0"
          },
          {
            "name": "sharp",
            "version": "^0.21.3"
          }
        ],
        "devDependencies": [
          {
            "name": "@babel/cli",
            "version": "^7.0.0"
          },
          {
            "name": "@babel/core",
            "version": "^7.0.0"
          },
          {
            "name": "babel-preset-gatsby-package",
            "version": "^0.1.3"
          },
          {
            "name": "cross-env",
            "version": "^5.1.4"
          }
        ],
        "peerDependencies": [
          {
            "name": "gatsby",
            "version": "^2.0.0"
          }
        ],
        "optionalDependecies": [],
        "bundledDependecies": []
      },
      "parent": null,
      "children": [],
      "internal": {
        "contentDigest": "2d5de4592ffb0a449d2ffda8ef0b8c8b",
        "type": "SitePlugin",
        "owner": "internal-data-bridge"
      }
    },
    "85b0d20d-d20b-5ebb-9609-951b47f8f842": {
      "resolve": "/Users/randyphallla/Documents/GitHub/randyphalla.github.io/node_modules/gatsby-plugin-prefetch-google-fonts",
      "id": "85b0d20d-d20b-5ebb-9609-951b47f8f842",
      "name": "gatsby-plugin-prefetch-google-fonts",
      "version": "1.4.0",
      "pluginOptions": {
        "plugins": [],
        "fonts": [
          {
            "family": "Montserrat",
            "variants": [
              "600",
              "700"
            ]
          },
          {
            "family": "Raleway",
            "variants": [
              "200",
              "500",
              "600",
              "700"
            ]
          }
        ]
      },
      "nodeAPIs": [
        "onPreBootstrap"
      ],
      "browserAPIs": [],
      "ssrAPIs": [
        "onRenderBody"
      ],
      "pluginFilepath": "/Users/randyphallla/Documents/GitHub/randyphalla.github.io/node_modules/gatsby-plugin-prefetch-google-fonts",
      "packageJson": {
        "name": "gatsby-plugin-prefetch-google-fonts",
        "description": "A Gatsby plugin to download and prefetch [Google Fonts](https://fonts.google.com/). Can increase performance as opposed to loading webfonts from Google's external stylesheet.",
        "version": "1.4.0",
        "main": "gatsby-ssr.js",
        "keywords": [
          "gatsby-plugin",
          "gatsby",
          "plugin",
          "web",
          "font",
          "loader",
          "google",
          "webfont",
          "webfontloader",
          "prefetch",
          "download",
          "downloader",
          "local"
        ],
        "author": {
          "name": "Kennedy Rose",
          "email": "krose@escaladesports.com"
        },
        "license": "MIT",
        "dependencies": [
          {
            "name": "@babel/runtime",
            "version": "^7.2.0"
          },
          {
            "name": "clean-css",
            "version": "^4.2.1"
          },
          {
            "name": "download",
            "version": "^7.1.0"
          },
          {
            "name": "fs-extra",
            "version": "^7.0.0"
          },
          {
            "name": "get-urls",
            "version": "^8.0.0"
          },
          {
            "name": "globby",
            "version": "^8.0.1"
          },
          {
            "name": "google-fonts-plugin",
            "version": "2.0.2"
          },
          {
            "name": "object-hash",
            "version": "^1.3.0"
          }
        ],
        "devDependencies": [
          {
            "name": "@babel/cli",
            "version": "^7.1.2"
          },
          {
            "name": "@babel/core",
            "version": "^7.1.2"
          },
          {
            "name": "@babel/plugin-proposal-class-properties",
            "version": "^7.1.0"
          },
          {
            "name": "@babel/plugin-proposal-decorators",
            "version": "^7.1.2"
          },
          {
            "name": "@babel/plugin-proposal-do-expressions",
            "version": "^7.0.0"
          },
          {
            "name": "@babel/plugin-proposal-export-default-from",
            "version": "^7.0.0"
          },
          {
            "name": "@babel/plugin-proposal-export-namespace-from",
            "version": "^7.0.0"
          },
          {
            "name": "@babel/plugin-proposal-function-bind",
            "version": "^7.0.0"
          },
          {
            "name": "@babel/plugin-proposal-function-sent",
            "version": "^7.1.0"
          },
          {
            "name": "@babel/plugin-proposal-json-strings",
            "version": "^7.0.0"
          },
          {
            "name": "@babel/plugin-proposal-logical-assignment-operators",
            "version": "^7.0.0"
          },
          {
            "name": "@babel/plugin-proposal-nullish-coalescing-operator",
            "version": "^7.0.0"
          },
          {
            "name": "@babel/plugin-proposal-numeric-separator",
            "version": "^7.0.0"
          },
          {
            "name": "@babel/plugin-proposal-optional-chaining",
            "version": "^7.0.0"
          },
          {
            "name": "@babel/plugin-proposal-pipeline-operator",
            "version": "^7.0.0"
          },
          {
            "name": "@babel/plugin-proposal-throw-expressions",
            "version": "^7.0.0"
          },
          {
            "name": "@babel/plugin-syntax-dynamic-import",
            "version": "^7.0.0"
          },
          {
            "name": "@babel/plugin-syntax-import-meta",
            "version": "^7.0.0"
          },
          {
            "name": "@babel/plugin-syntax-jsx",
            "version": "^7.2.0"
          },
          {
            "name": "@babel/plugin-transform-runtime",
            "version": "^7.1.0"
          },
          {
            "name": "@babel/preset-env",
            "version": "^7.1.0"
          },
          {
            "name": "@babel/preset-react",
            "version": "^7.0.0"
          },
          {
            "name": "child-process-async",
            "version": "^1.0.1"
          },
          {
            "name": "child-process-promise",
            "version": "^2.2.1"
          },
          {
            "name": "emotion",
            "version": "^9.2.6"
          },
          {
            "name": "emotion-server",
            "version": "^9.2.6"
          },
          {
            "name": "enzyme",
            "version": "^3.5.0"
          },
          {
            "name": "enzyme-adapter-react-16",
            "version": "^1.3.0"
          },
          {
            "name": "eslint",
            "version": "^5.2.0"
          },
          {
            "name": "eslint-config-escalade-sports",
            "version": "^1.0.1"
          },
          {
            "name": "gatsby",
            "version": "^2.0.19"
          },
          {
            "name": "gatsby-plugin-emotion",
            "version": "2.0.5"
          },
          {
            "name": "husky",
            "version": "^0.14.3"
          },
          {
            "name": "identity-obj-proxy",
            "version": "^3.0.0"
          },
          {
            "name": "isomorphic-fetch",
            "version": "^2.2.1"
          },
          {
            "name": "jest",
            "version": "^23.4.2"
          },
          {
            "name": "jest-dom",
            "version": "^1.12.0"
          },
          {
            "name": "lint-staged",
            "version": "^7.2.0"
          },
          {
            "name": "netlify-cms",
            "version": "^1.9.3"
          },
          {
            "name": "netlify-lambda",
            "version": "^0.4.0"
          },
          {
            "name": "npm-run-all",
            "version": "^4.1.3"
          },
          {
            "name": "opn-cli",
            "version": "^3.1.0"
          },
          {
            "name": "react",
            "version": "^16.4.0"
          },
          {
            "name": "react-dom",
            "version": "^16.4.0"
          },
          {
            "name": "react-helmet",
            "version": "^5.2.0"
          },
          {
            "name": "react-netlify-form",
            "version": "^2.0.7"
          },
          {
            "name": "react-no-ssr",
            "version": "^1.1.0"
          },
          {
            "name": "react-test-renderer",
            "version": "^16.4.2"
          },
          {
            "name": "react-testing-library",
            "version": "^4.1.7"
          },
          {
            "name": "request",
            "version": "^2.87.0"
          },
          {
            "name": "statable",
            "version": "^0.3.2"
          },
          {
            "name": "static-server",
            "version": "^2.2.1"
          },
          {
            "name": "strip-html-comments",
            "version": "^1.0.0"
          },
          {
            "name": "toml",
            "version": "^2.3.3"
          },
          {
            "name": "wt-cli",
            "version": "^10.0.3"
          }
        ],
        "peerDependencies": [],
        "optionalDependecies": [],
        "bundledDependecies": []
      },
      "parent": null,
      "children": [],
      "internal": {
        "contentDigest": "011f44c53a3b2328aaa0a682cabb00b2",
        "type": "SitePlugin",
        "owner": "internal-data-bridge"
      }
    },
    "54d0fd21-71eb-5f71-bda2-f9c638c048ad": {
      "resolve": "/Users/randyphallla/Documents/GitHub/randyphalla.github.io/node_modules/gatsby-plugin-styled-components",
      "id": "54d0fd21-71eb-5f71-bda2-f9c638c048ad",
      "name": "gatsby-plugin-styled-components",
      "version": "3.0.7",
      "pluginOptions": {
        "plugins": [],
        "displayName": false
      },
      "nodeAPIs": [
        "onCreateBabelConfig"
      ],
      "browserAPIs": [],
      "ssrAPIs": [
        "wrapRootElement",
        "onRenderBody"
      ],
      "pluginFilepath": "/Users/randyphallla/Documents/GitHub/randyphalla.github.io/node_modules/gatsby-plugin-styled-components",
      "packageJson": {
        "name": "gatsby-plugin-styled-components",
        "description": "Gatsby plugin to add support for styled components",
        "version": "3.0.7",
        "main": "index.js",
        "keywords": [
          "gatsby",
          "gatsby-plugin",
          "styled-components"
        ],
        "author": {
          "name": "Guten Ye",
          "email": "ywzhaifei@gmail.com"
        },
        "license": "MIT",
        "dependencies": [
          {
            "name": "@babel/runtime",
            "version": "^7.0.0"
          }
        ],
        "devDependencies": [
          {
            "name": "@babel/cli",
            "version": "^7.0.0"
          },
          {
            "name": "@babel/core",
            "version": "^7.0.0"
          },
          {
            "name": "babel-preset-gatsby-package",
            "version": "^0.1.4"
          },
          {
            "name": "cross-env",
            "version": "^5.2.0"
          }
        ],
        "peerDependencies": [
          {
            "name": "babel-plugin-styled-components",
            "version": ">1.5.0"
          },
          {
            "name": "gatsby",
            "version": "^2.0.32"
          },
          {
            "name": "styled-components",
            "version": ">=2.0.0"
          }
        ],
        "optionalDependecies": [],
        "bundledDependecies": []
      },
      "parent": null,
      "children": [],
      "internal": {
        "contentDigest": "33984f39aaf45d1e537153efc885ad14",
        "type": "SitePlugin",
        "owner": "internal-data-bridge"
      }
    },
    "7374ebf2-d961-52ee-92a2-c25e7cb387a9": {
      "resolve": "/Users/randyphallla/Documents/GitHub/randyphalla.github.io",
      "id": "7374ebf2-d961-52ee-92a2-c25e7cb387a9",
      "name": "default-site-plugin",
      "version": "d3fabb598b99761fbfdcd55f15d2128c",
      "pluginOptions": {
        "plugins": []
      },
      "nodeAPIs": [],
      "browserAPIs": [],
      "ssrAPIs": [],
      "pluginFilepath": "/Users/randyphallla/Documents/GitHub/randyphalla.github.io",
      "packageJson": {
        "name": "gatsby-starter-default",
        "description": "A simple starter to get up and developing quickly with Gatsby",
        "version": "0.1.0",
        "keywords": [
          "gatsby"
        ],
        "author": "Kyle Mathews <mathews.kyle@gmail.com>",
        "license": "MIT",
        "dependencies": [
          {
            "name": "babel-plugin-styled-components",
            "version": "^1.10.0"
          },
          {
            "name": "gatsby",
            "version": "^2.1.23"
          },
          {
            "name": "gatsby-image",
            "version": "^2.0.31"
          },
          {
            "name": "gatsby-plugin-manifest",
            "version": "^2.0.22"
          },
          {
            "name": "gatsby-plugin-offline",
            "version": "^2.0.24"
          },
          {
            "name": "gatsby-plugin-prefetch-google-fonts",
            "version": "^1.4.0"
          },
          {
            "name": "gatsby-plugin-react-helmet",
            "version": "^3.0.8"
          },
          {
            "name": "gatsby-plugin-sass",
            "version": "^2.0.10"
          },
          {
            "name": "gatsby-plugin-sharp",
            "version": "^2.0.25"
          },
          {
            "name": "gatsby-plugin-styled-components",
            "version": "^3.0.7"
          },
          {
            "name": "gatsby-source-filesystem",
            "version": "^2.0.23"
          },
          {
            "name": "gatsby-transformer-sharp",
            "version": "^2.1.15"
          },
          {
            "name": "node-sass",
            "version": "^4.11.0"
          },
          {
            "name": "prop-types",
            "version": "^15.7.2"
          },
          {
            "name": "react",
            "version": "^16.8.4"
          },
          {
            "name": "react-dom",
            "version": "^16.8.4"
          },
          {
            "name": "react-helmet",
            "version": "^5.2.0"
          },
          {
            "name": "styled-components",
            "version": "^4.2.0"
          }
        ],
        "devDependencies": [
          {
            "name": "prettier",
            "version": "^1.16.4"
          },
          {
            "name": "sass",
            "version": "^1.17.2"
          }
        ],
        "peerDependencies": [],
        "optionalDependecies": [],
        "bundledDependecies": []
      },
      "parent": null,
      "children": [],
      "internal": {
        "contentDigest": "40ac19b19cc67ae2784e51e777dd43cb",
        "type": "SitePlugin",
        "owner": "internal-data-bridge"
      }
    },
    "2cce34b6-f031-5cef-8637-f11a0674c13d": {
      "resolve": "/Users/randyphallla/Documents/GitHub/randyphalla.github.io/node_modules/gatsby-plugin-page-creator",
      "id": "2cce34b6-f031-5cef-8637-f11a0674c13d",
      "name": "gatsby-plugin-page-creator",
      "version": "2.0.9",
      "pluginOptions": {
        "plugins": [],
        "path": "/Users/randyphallla/Documents/GitHub/randyphalla.github.io/src/pages",
        "pathCheck": false
      },
      "nodeAPIs": [
        "createPagesStatefully"
      ],
      "browserAPIs": [],
      "ssrAPIs": [],
      "pluginFilepath": "/Users/randyphallla/Documents/GitHub/randyphalla.github.io/node_modules/gatsby-plugin-page-creator",
      "packageJson": {
        "name": "gatsby-plugin-page-creator",
        "description": "Gatsby plugin that automatically creates pages from React components in specified directories",
        "version": "2.0.9",
        "main": "index.js",
        "keywords": [
          "gatsby",
          "gatsby-plugin"
        ],
        "author": {
          "name": "Kyle Mathews",
          "email": "mathews.kyle@gmail.com"
        },
        "license": "MIT",
        "dependencies": [
          {
            "name": "@babel/runtime",
            "version": "^7.0.0"
          },
          {
            "name": "bluebird",
            "version": "^3.5.0"
          },
          {
            "name": "chokidar",
            "version": "^2.1.2"
          },
          {
            "name": "fs-exists-cached",
            "version": "^1.0.0"
          },
          {
            "name": "glob",
            "version": "^7.1.1"
          },
          {
            "name": "lodash",
            "version": "^4.17.10"
          },
          {
            "name": "micromatch",
            "version": "^3.1.10"
          },
          {
            "name": "parse-filepath",
            "version": "^1.0.1"
          },
          {
            "name": "slash",
            "version": "^1.0.0"
          }
        ],
        "devDependencies": [
          {
            "name": "@babel/cli",
            "version": "^7.0.0"
          },
          {
            "name": "@babel/core",
            "version": "^7.0.0"
          },
          {
            "name": "babel-preset-gatsby-package",
            "version": "^0.1.3"
          },
          {
            "name": "cross-env",
            "version": "^5.0.5"
          }
        ],
        "peerDependencies": [
          {
            "name": "gatsby",
            "version": "^2.0.0"
          }
        ],
        "optionalDependecies": [],
        "bundledDependecies": []
      },
      "parent": null,
      "children": [],
      "internal": {
        "contentDigest": "6ec0e0140d22805ebd900ad8fd8cb672",
        "type": "SitePlugin",
        "owner": "internal-data-bridge"
      }
    },
    "Site": {
      "siteMetadata": {
        "title": "Gatsby Default Starter",
        "description": "Kick off your next, great Gatsby project with this default starter. This barebones starter ships with the main Gatsby configuration files you might need.",
        "author": "@gatsbyjs"
      },
      "pathPrefix": "",
      "polyfill": true,
      "buildTime": "2019-04-01T03:54:39.552Z",
      "id": "Site",
      "parent": null,
      "children": [],
      "internal": {
        "contentDigest": "f38dff58db9bba717bddc17cc3032ad3",
        "type": "Site",
        "owner": "internal-data-bridge"
      }
    },
    "e1891fdf-af9d-5079-a104-a7095dc738a4": {
      "id": "e1891fdf-af9d-5079-a104-a7095dc738a4",
      "children": [],
      "parent": null,
      "internal": {
        "contentDigest": "0ced5bb1e6231f9b478cc99e322c4630",
        "type": "Directory",
        "description": "Directory \"src/images\"",
        "owner": "gatsby-source-filesystem"
      },
      "sourceInstanceName": "images",
      "absolutePath": "/Users/randyphallla/Documents/GitHub/randyphalla.github.io/src/images",
      "relativePath": "",
      "extension": "",
      "size": 128,
      "prettySize": "128 B",
      "modifiedTime": "2019-03-27T23:20:05.745Z",
      "accessTime": "2019-04-01T03:54:42.114Z",
      "changeTime": "2019-03-27T23:20:05.745Z",
      "birthTime": "2019-03-27T23:20:05.743Z",
      "root": "/",
      "dir": "/Users/randyphallla/Documents/GitHub/randyphalla.github.io/src",
      "base": "images",
      "ext": "",
      "name": "images",
      "relativeDirectory": "..",
      "dev": 16777223,
      "mode": 16877,
      "nlink": 4,
      "uid": 501,
      "gid": 20,
      "rdev": 0,
      "blksize": 4096,
      "ino": 8674178453,
      "blocks": 0,
      "atimeMs": 1554090882114.1174,
      "mtimeMs": 1553728805745.1824,
      "ctimeMs": 1553728805745.1824,
      "birthtimeMs": 1553728805742.8247,
      "atime": "2019-04-01T03:54:42.114Z",
      "mtime": "2019-03-27T23:20:05.745Z",
      "ctime": "2019-03-27T23:20:05.745Z",
      "birthtime": "2019-03-27T23:20:05.743Z"
    },
    "21c655d1-3d5f-568e-be0e-0641a14fcc4d": {
      "id": "21c655d1-3d5f-568e-be0e-0641a14fcc4d",
      "children": [
        "64a019e5-5277-5091-816d-9d4cdd53b186"
      ],
      "parent": null,
      "internal": {
        "contentDigest": "4a9773549091c227cd2eb82ccd9c5e3a",
        "type": "File",
        "mediaType": "image/png",
        "description": "File \"src/images/gatsby-icon.png\"",
        "owner": "gatsby-source-filesystem"
      },
      "sourceInstanceName": "images",
      "absolutePath": "/Users/randyphallla/Documents/GitHub/randyphalla.github.io/src/images/gatsby-icon.png",
      "relativePath": "gatsby-icon.png",
      "extension": "png",
      "size": 21212,
      "prettySize": "21.2 kB",
      "modifiedTime": "2019-03-27T23:20:05.746Z",
      "accessTime": "2019-04-01T03:13:17.550Z",
      "changeTime": "2019-03-27T23:20:05.746Z",
      "birthTime": "2019-03-27T23:20:05.745Z",
      "root": "/",
      "dir": "/Users/randyphallla/Documents/GitHub/randyphalla.github.io/src/images",
      "base": "gatsby-icon.png",
      "ext": ".png",
      "name": "gatsby-icon",
      "relativeDirectory": "",
      "dev": 16777223,
      "mode": 33188,
      "nlink": 1,
      "uid": 501,
      "gid": 20,
      "rdev": 0,
      "blksize": 4096,
      "ino": 8674178455,
      "blocks": 48,
      "atimeMs": 1554088397549.925,
      "mtimeMs": 1553728805745.8506,
      "ctimeMs": 1553728805745.8506,
      "birthtimeMs": 1553728805745.1707,
      "atime": "2019-04-01T03:13:17.550Z",
      "mtime": "2019-03-27T23:20:05.746Z",
      "ctime": "2019-03-27T23:20:05.746Z",
      "birthtime": "2019-03-27T23:20:05.745Z"
    },
    "64a019e5-5277-5091-816d-9d4cdd53b186": {
      "id": "64a019e5-5277-5091-816d-9d4cdd53b186",
      "children": [],
      "parent": "21c655d1-3d5f-568e-be0e-0641a14fcc4d",
      "internal": {
        "contentDigest": "4a9773549091c227cd2eb82ccd9c5e3a",
        "type": "ImageSharp",
        "owner": "gatsby-transformer-sharp"
      }
    },
    "ae05fd28-40c5-5df7-86f1-dab73e90e5d8": {
      "id": "ae05fd28-40c5-5df7-86f1-dab73e90e5d8",
      "children": [
        "f5f75236-7143-53cd-a1ba-5536ea77f15c"
      ],
      "parent": null,
      "internal": {
        "contentDigest": "6d91c86c0fde632ba4cd01062fd9ccfa",
        "type": "File",
        "mediaType": "image/png",
        "description": "File \"src/images/gatsby-astronaut.png\"",
        "owner": "gatsby-source-filesystem"
      },
      "sourceInstanceName": "images",
      "absolutePath": "/Users/randyphallla/Documents/GitHub/randyphalla.github.io/src/images/gatsby-astronaut.png",
      "relativePath": "gatsby-astronaut.png",
      "extension": "png",
      "size": 167273,
      "prettySize": "167 kB",
      "modifiedTime": "2019-03-27T23:20:05.745Z",
      "accessTime": "2019-04-01T03:13:14.532Z",
      "changeTime": "2019-03-27T23:20:05.745Z",
      "birthTime": "2019-03-27T23:20:05.743Z",
      "root": "/",
      "dir": "/Users/randyphallla/Documents/GitHub/randyphalla.github.io/src/images",
      "base": "gatsby-astronaut.png",
      "ext": ".png",
      "name": "gatsby-astronaut",
      "relativeDirectory": "",
      "dev": 16777223,
      "mode": 33188,
      "nlink": 1,
      "uid": 501,
      "gid": 20,
      "rdev": 0,
      "blksize": 4096,
      "ino": 8674178454,
      "blocks": 328,
      "atimeMs": 1554088394531.823,
      "mtimeMs": 1553728805745.0178,
      "ctimeMs": 1553728805745.0178,
      "birthtimeMs": 1553728805742.8909,
      "atime": "2019-04-01T03:13:14.532Z",
      "mtime": "2019-03-27T23:20:05.745Z",
      "ctime": "2019-03-27T23:20:05.745Z",
      "birthtime": "2019-03-27T23:20:05.743Z"
    },
    "f5f75236-7143-53cd-a1ba-5536ea77f15c": {
      "id": "f5f75236-7143-53cd-a1ba-5536ea77f15c",
      "children": [],
      "parent": "ae05fd28-40c5-5df7-86f1-dab73e90e5d8",
      "internal": {
        "contentDigest": "6d91c86c0fde632ba4cd01062fd9ccfa",
        "type": "ImageSharp",
        "owner": "gatsby-transformer-sharp"
      }
    },
    "SitePage /404/": {
      "jsonName": "404-22d",
      "internalComponentName": "Component404",
      "path": "/404/",
      "component": "/Users/randyphallla/Documents/GitHub/randyphalla.github.io/src/pages/404.js",
      "componentChunkName": "component---src-pages-404-js",
      "context": {},
      "pluginCreator___NODE": "2cce34b6-f031-5cef-8637-f11a0674c13d",
      "pluginCreatorId": "2cce34b6-f031-5cef-8637-f11a0674c13d",
      "componentPath": "/Users/randyphallla/Documents/GitHub/randyphalla.github.io/src/pages/404.js",
      "id": "SitePage /404/",
      "parent": null,
      "children": [],
      "internal": {
        "type": "SitePage",
        "contentDigest": "d1447dd741b537163e405f30c10ec59a",
        "description": "2cce34b6-f031-5cef-8637-f11a0674c13d",
        "owner": "internal-data-bridge"
      }
    },
    "SitePage /about/": {
      "jsonName": "about-f34",
      "internalComponentName": "ComponentAbout",
      "path": "/about/",
      "component": "/Users/randyphallla/Documents/GitHub/randyphalla.github.io/src/pages/about.js",
      "componentChunkName": "component---src-pages-about-js",
      "context": {},
      "pluginCreator___NODE": "2cce34b6-f031-5cef-8637-f11a0674c13d",
      "pluginCreatorId": "2cce34b6-f031-5cef-8637-f11a0674c13d",
      "componentPath": "/Users/randyphallla/Documents/GitHub/randyphalla.github.io/src/pages/about.js",
      "id": "SitePage /about/",
      "parent": null,
      "children": [],
      "internal": {
        "type": "SitePage",
        "contentDigest": "c689bb801a6b2f922c2919ca8483d427",
        "description": "2cce34b6-f031-5cef-8637-f11a0674c13d",
        "owner": "internal-data-bridge"
      }
    },
    "SitePage /contact/": {
      "jsonName": "contact-26a",
      "internalComponentName": "ComponentContact",
      "path": "/contact/",
      "component": "/Users/randyphallla/Documents/GitHub/randyphalla.github.io/src/pages/contact.js",
      "componentChunkName": "component---src-pages-contact-js",
      "context": {},
      "pluginCreator___NODE": "2cce34b6-f031-5cef-8637-f11a0674c13d",
      "pluginCreatorId": "2cce34b6-f031-5cef-8637-f11a0674c13d",
      "componentPath": "/Users/randyphallla/Documents/GitHub/randyphalla.github.io/src/pages/contact.js",
      "id": "SitePage /contact/",
      "parent": null,
      "children": [],
      "internal": {
        "type": "SitePage",
        "contentDigest": "70f82ab6d99b0a225b51ba0a2045234a",
        "description": "2cce34b6-f031-5cef-8637-f11a0674c13d",
        "owner": "internal-data-bridge"
      }
    },
    "SitePage /": {
      "jsonName": "index",
      "internalComponentName": "ComponentIndex",
      "path": "/",
      "component": "/Users/randyphallla/Documents/GitHub/randyphalla.github.io/src/pages/index.js",
      "componentChunkName": "component---src-pages-index-js",
      "context": {},
      "pluginCreator___NODE": "2cce34b6-f031-5cef-8637-f11a0674c13d",
      "pluginCreatorId": "2cce34b6-f031-5cef-8637-f11a0674c13d",
      "componentPath": "/Users/randyphallla/Documents/GitHub/randyphalla.github.io/src/pages/index.js",
      "id": "SitePage /",
      "parent": null,
      "children": [],
      "internal": {
        "type": "SitePage",
        "contentDigest": "cb8b2d87dce02571c9f6d5e5dd32016b",
        "description": "2cce34b6-f031-5cef-8637-f11a0674c13d",
        "owner": "internal-data-bridge"
      }
    },
    "SitePage /portfolio/": {
      "jsonName": "portfolio-964",
      "internalComponentName": "ComponentPortfolio",
      "path": "/portfolio/",
      "component": "/Users/randyphallla/Documents/GitHub/randyphalla.github.io/src/pages/portfolio.js",
      "componentChunkName": "component---src-pages-portfolio-js",
      "context": {},
      "pluginCreator___NODE": "2cce34b6-f031-5cef-8637-f11a0674c13d",
      "pluginCreatorId": "2cce34b6-f031-5cef-8637-f11a0674c13d",
      "componentPath": "/Users/randyphallla/Documents/GitHub/randyphalla.github.io/src/pages/portfolio.js",
      "id": "SitePage /portfolio/",
      "parent": null,
      "children": [],
      "internal": {
        "type": "SitePage",
        "contentDigest": "e90d7170f246965597118062f2b1461e",
        "description": "2cce34b6-f031-5cef-8637-f11a0674c13d",
        "owner": "internal-data-bridge"
      }
    },
    "SitePage /404.html": {
      "jsonName": "404-html-516",
      "internalComponentName": "Component404Html",
      "path": "/404.html",
      "component": "/Users/randyphallla/Documents/GitHub/randyphalla.github.io/src/pages/404.js",
      "componentChunkName": "component---src-pages-404-js",
      "context": {},
      "pluginCreator___NODE": "f795702c-a3b8-5a88-88ee-5d06019d44fa",
      "pluginCreatorId": "f795702c-a3b8-5a88-88ee-5d06019d44fa",
      "componentPath": "/Users/randyphallla/Documents/GitHub/randyphalla.github.io/src/pages/404.js",
      "id": "SitePage /404.html",
      "parent": null,
      "children": [],
      "internal": {
        "type": "SitePage",
        "contentDigest": "c1c1116f3ef9cb27d7d84745ad72a4c3",
        "description": "f795702c-a3b8-5a88-88ee-5d06019d44fa",
        "owner": "internal-data-bridge"
      }
    }
  },
  "status": {
    "plugins": {},
    "PLUGINS_HASH": "93c70c8019613c9f207f6caf3e31774e"
  },
  "componentDataDependencies": {
    "nodes": {
      "Site": [
        "sq--src-components-layout-layout-js",
        "sq--src-components-seo-js"
      ],
      "ae05fd28-40c5-5df7-86f1-dab73e90e5d8": [
        "sq--src-components-image-js"
      ],
      "f5f75236-7143-53cd-a1ba-5536ea77f15c": [
        "sq--src-components-image-js"
      ]
    },
    "connections": {}
  },
  "jsonDataPaths": {
    "dev-404-page-5f9": "920/path---dev-404-page-5-f-9-fab-NZuapzHg3X9TaN1iIixfv1W23E",
    "sq--src-components-layout-js": 755544856,
    "sq--src-components-seo-js": 1025518380,
    "404-22d": "44/path---404-22-d-bce-NZuapzHg3X9TaN1iIixfv1W23E",
    "about-f34": "125/path---about-f-34-4c2-NZuapzHg3X9TaN1iIixfv1W23E",
    "contact-26a": "686/path---contact-26-a-cd9-NZuapzHg3X9TaN1iIixfv1W23E",
    "index": "173/path---index-6a9-NZuapzHg3X9TaN1iIixfv1W23E",
    "portfolio-964": "107/path---portfolio-964-7f6-NZuapzHg3X9TaN1iIixfv1W23E",
    "404-html-516": "164/path---404-html-516-62a-NZuapzHg3X9TaN1iIixfv1W23E",
    "sq--src-components-image-js": 2011440971,
    "sq--src-components-layout-layout-js": 755544856
  },
  "components": {
    "/Users/randyphallla/Documents/GitHub/randyphalla.github.io/src/pages/404.js": {
      "query": "",
      "componentPath": "/Users/randyphallla/Documents/GitHub/randyphalla.github.io/src/pages/404.js"
    },
    "/Users/randyphallla/Documents/GitHub/randyphalla.github.io/src/pages/about.js": {
      "query": "",
      "componentPath": "/Users/randyphallla/Documents/GitHub/randyphalla.github.io/src/pages/about.js"
    },
    "/Users/randyphallla/Documents/GitHub/randyphalla.github.io/src/pages/contact.js": {
      "query": "",
      "componentPath": "/Users/randyphallla/Documents/GitHub/randyphalla.github.io/src/pages/contact.js"
    },
    "/Users/randyphallla/Documents/GitHub/randyphalla.github.io/src/pages/index.js": {
      "query": "",
      "componentPath": "/Users/randyphallla/Documents/GitHub/randyphalla.github.io/src/pages/index.js"
    },
    "/Users/randyphallla/Documents/GitHub/randyphalla.github.io/src/pages/portfolio.js": {
      "query": "",
      "componentPath": "/Users/randyphallla/Documents/GitHub/randyphalla.github.io/src/pages/portfolio.js"
    }
  },
  "staticQueryComponents": {
    "sq--src-components-image-js": {
      "name": "usersRandyphalllaDocumentsGitHubRandyphallaGithubIoSrcComponentsImageJs2011440971",
      "componentPath": "/Users/randyphallla/Documents/GitHub/randyphalla.github.io/src/components/image.js",
      "id": "sq--src-components-image-js",
      "jsonName": "sq--src-components-image-js",
      "query": "query usersRandyphalllaDocumentsGitHubRandyphallaGithubIoSrcComponentsImageJs2011440971 {\n  placeholderImage: file(relativePath: {eq: \"gatsby-astronaut.png\"}) {\n    childImageSharp {\n      fluid(maxWidth: 300) {\n        ...GatsbyImageSharpFluid\n      }\n    }\n  }\n}\n\nfragment GatsbyImageSharpFluid on ImageSharpFluid {\n  base64\n  aspectRatio\n  src\n  srcSet\n  sizes\n}\n",
      "hash": 2011440971
    },
    "sq--src-components-seo-js": {
      "name": "DefaultSEOQuery",
      "componentPath": "/Users/randyphallla/Documents/GitHub/randyphalla.github.io/src/components/seo.js",
      "id": "sq--src-components-seo-js",
      "jsonName": "sq--src-components-seo-js",
      "query": "query DefaultSEOQuery {\n  site {\n    siteMetadata {\n      title\n      description\n      author\n    }\n  }\n}\n",
      "hash": 1025518380
    },
    "sq--src-components-layout-layout-js": {
      "name": "SiteTitleQuery",
      "componentPath": "/Users/randyphallla/Documents/GitHub/randyphalla.github.io/src/components/layout/layout.js",
      "id": "sq--src-components-layout-layout-js",
      "jsonName": "sq--src-components-layout-layout-js",
      "query": "query SiteTitleQuery {\n  site {\n    siteMetadata {\n      title\n    }\n  }\n}\n",
      "hash": 755544856
    }
  }
}